datasette_schema_versions/__init__.py
datasette_schema_versions-0.3.dist-info/METADATA
datasette_schema_versions-0.3.dist-info/WHEEL
datasette_schema_versions-0.3.dist-info/entry_points.txt
datasette_schema_versions-0.3.dist-info/top_level.txt
datasette_schema_versions-0.3.dist-info/RECORD
