Metadata-Version: 2.1
Name: datasette-schema-versions
Version: 0.3
Summary: Datasette plugin that shows the schema version of every attached database
Home-page: https://github.com/simonw/datasette-schema-versions
Author: Simon Willison
License: Apache License, Version 2.0
Project-URL: Issues, https://github.com/simonw/datasette-schema-versions/issues
Project-URL: CI, https://github.com/simonw/datasette-schema-versions/actions
Project-URL: Changelog, https://github.com/simonw/datasette-schema-versions/releases
Requires-Dist: datasette
Provides-Extra: test
Requires-Dist: pytest ; extra == 'test'
Requires-Dist: pytest-asyncio ; extra == 'test'
Requires-Dist: httpx ; extra == 'test'
Requires-Dist: sqlite-utils ; extra == 'test'
